s3hive/__init__.py
s3hive/bucket.py
s3hive-1.0.0.dist-info/LICENCE
s3hive-1.0.0.dist-info/METADATA
s3hive-1.0.0.dist-info/WHEEL
s3hive-1.0.0.dist-info/top_level.txt
s3hive-1.0.0.dist-info/RECORD
