Metadata-Version: 2.1
Name: s3hive
Version: 1.0.0
Summary: A tool built on top of boto3 that allows you to easily manage your S3 buckets.
Home-page: https://github.com/sotberd/s3hive
Author: sotberd
Author-email: sotiriosn.berdes@gmail.com
License: MIT
Keywords: s3,boto3,aws,bucket,s3hive
Platform: UNKNOWN
Classifier: Programming Language :: Python :: 3
Classifier: License :: OSI Approved :: MIT License
Classifier: Operating System :: OS Independent
Requires-Python: >=3.8
Requires-Dist: boto3
Requires-Dist: tqdm
